# Table of Contents

* [包装类型赋值解读](#包装类型赋值解读)
    * [包装类型是什么](#包装类型是什么)
    * [包装类型赋值和基本类型的区别](#包装类型赋值和基本类型的区别)

# 包装类型赋值解读

## 包装类型是什么

包装类型是Java为基本类型对应定义的类，其具备了对应基本类型的值以及对值的相关操作行为。

对应关系：

| 基本类型 | 包装类型 |
| --- | --- |
| char | Character |
| byte | Byte |
| short | Short |
| int | Integer |
| long | Long |
| float | Float |
| double | Double |
| boolean | Boolean |


## 包装类型赋值和基本类型的区别

其实对于包装类型有工作经验的人也不需要再讲概念了，其实最关心的是两者赋值有什么区别。

先讲基本数据类型赋值（本篇以int和Integer举例，其他其实类似），举个例子：

```
public class Main {

    public static int a = 1;

    public int b = 2;

    public void cal() {
        int c = a + b;
    }

}
```

为了全面分析，例子定义了静态成员变量、普通成员变量、局部变量，我们就分析分析这个值赋了到底是在哪。

其实有字节码学习经验的都知道Java中每个方法都会有自己的方法栈用来存放局部变量的值或是引用类型的内存指针，随着的方法的生命周期而存在，所以局部变量在栈中。

而静态成员变量归属于类，显然不会在堆内存中，其存在于JVM的元数据区（Java8），而普通成员变量是跟随对象存在的，只有`new`出来的对象才真正持有它，所以普通成员变量包含在对象中由堆内存管理。

我们可以具体看看上面代码字节码长啥样：

```
public class com.xyz.study.Main
  minor version: 0
  major version: 52
  flags: (0x0021) ACC_PUBLIC, ACC_SUPER
  this_class: #4                          // com/xyz/study/Main
  super_class: #5                         // java/lang/Object
  interfaces: 0, fields: 2, methods: 3, attributes: 1
Constant pool:
   #1 = Methodref          #5.#21         // java/lang/Object."<init>":()V
   #2 = Fieldref           #4.#22         // com/xyz/study/Main.b:I
   #3 = Fieldref           #4.#23         // com/xyz/study/Main.a:I
   #4 = Class              #24            // com/xyz/study/Main
   #5 = Class              #25            // java/lang/Object
   #6 = Utf8               a
   #7 = Utf8               I
   #8 = Utf8               b
   #9 = Utf8               <init>
  #10 = Utf8               ()V
  #11 = Utf8               Code
  #12 = Utf8               LineNumberTable
  #13 = Utf8               LocalVariableTable
  #14 = Utf8               this
  #15 = Utf8               Lcom/xyz/study/Main;
  #16 = Utf8               cal
  #17 = Utf8               c
  #18 = Utf8               <clinit>
  #19 = Utf8               SourceFile
  #20 = Utf8               Main.java
  #21 = NameAndType        #9:#10         // "<init>":()V
  #22 = NameAndType        #8:#7          // b:I
  #23 = NameAndType        #6:#7          // a:I
  #24 = Utf8               com/xyz/study/Main
  #25 = Utf8               java/lang/Object
{
  public static int a;
    descriptor: I
    flags: (0x0009) ACC_PUBLIC, ACC_STATIC

  public int b;
    descriptor: I
    flags: (0x0001) ACC_PUBLIC

  public com.xyz.study.Main();
    descriptor: ()V
    flags: (0x0001) ACC_PUBLIC
    Code:
      stack=2, locals=1, args_size=1
         0: aload_0
         1: invokespecial #1                  // Method java/lang/Object."<init>":()V
         4: aload_0
         5: iconst_2
         6: putfield      #2                  // Field b:I
         9: return
      LineNumberTable:
        line 7: 0
        line 11: 4
      LocalVariableTable:
        Start  Length  Slot  Name   Signature
            0      10     0  this   Lcom/xyz/study/Main;

  public void cal();
    descriptor: ()V
    flags: (0x0001) ACC_PUBLIC
    Code:
      stack=2, locals=2, args_size=1
         0: getstatic     #3                  // Field a:I
         3: aload_0
         4: getfield      #2                  // Field b:I
         7: iadd
         8: istore_1
         9: return
      LineNumberTable:
        line 14: 0
        line 15: 9
      LocalVariableTable:
        Start  Length  Slot  Name   Signature
            0      10     0  this   Lcom/xyz/study/Main;
            9       1     1     c   I

  static {};
    descriptor: ()V
    flags: (0x0008) ACC_STATIC
    Code:
      stack=1, locals=0, args_size=0
         0: iconst_1
         1: putstatic     #3                  // Field a:I
         4: return
      LineNumberTable:
        line 9: 0
}
SourceFile: "Main.java"
```

这里面提取出3个信息（假设基本能看懂上面的字节码，不懂先去学习字节码）：

1. 普通成员变量虽然我们这里直接赋值，其实赋值是构造对象时发生；
2. 局部变量存在于方法的本地变量表，故随方法而存在；
3. 静态成员变量赋值其实存在于静态代码块。


再讲包装类型的赋值，就基于上面的代码比较了：

```
public class Main {

    public static int a = 1;

    public static Integer A = -1;

    public int b = 2;

    public Integer B = -2;

    public void cal() {
        int c = a + b;
        Integer C = A + B;
    }

}
```

观察赋值，感觉和基本类型也没什么区别，这里就涉及到自动装箱（Java的语法糖），其实观察字节码就会发现，调用的是`Integer#valueOf`去完成初始化的。（相对应的将包装类型的值赋值给基本类型叫自动拆箱）

部分字节码：

```
...
  public com.xyz.study.Main();
    descriptor: ()V
    flags: (0x0001) ACC_PUBLIC
    Code:
      stack=2, locals=1, args_size=1
         0: aload_0
         1: invokespecial #1                  // Method java/lang/Object."<init>":()V
         4: aload_0
         5: iconst_2
         6: putfield      #2                  // Field b:I
         9: aload_0
        10: bipush        -2
        12: invokestatic  #3                  // Method java/lang/Integer.valueOf:(I)Ljava/lang/Integer;
        15: putfield      #4                  // Field B:Ljava/lang/Integer;
        18: return
      LineNumberTable:
        line 7: 0
        line 13: 4
        line 15: 9
      LocalVariableTable:
        Start  Length  Slot  Name   Signature
            0      19     0  this   Lcom/xyz/study/Main;
...
```